string_to_code/README.md
string_to_code/__init__.py
string_to_code/c_like_utils.py
string_to_code/core.py
string_to_code/string_to_code.py
string_to_code/to_ada.py
string_to_code/to_algol68.py
string_to_code/to_ballerina.py
string_to_code/to_bash.py
string_to_code/to_c.py
string_to_code/to_cobol.py
string_to_code/to_cpp.py
string_to_code/to_fortran90.py
string_to_code/to_haskell.py
string_to_code/to_java.py
string_to_code/to_kotlin.py
string_to_code/to_lisp.py
string_to_code/to_lua.py
string_to_code/to_nim.py
string_to_code/to_pascal.py
string_to_code/to_python3.py
string_to_code/to_rust.py
string_to_code/utils.py
string_to_code-0.5.0.dist-info/LICENSE
string_to_code-0.5.0.dist-info/METADATA
string_to_code-0.5.0.dist-info/WHEEL
string_to_code-0.5.0.dist-info/RECORD
