Metadata-Version: 2.3
Name: string-to-code
Version: 0.5.0
Summary: Generates a piece of messy code in a given language displaying a given string 
License: MIT
Keywords: code-generation
Author: piotr.idzik
Author-email: vil02@o2.pl
Requires-Python: >=3.10,<4.0.0
Classifier: License :: OSI Approved :: MIT License
Classifier: Programming Language :: Python :: 3
Classifier: Programming Language :: Python :: 3.10
Classifier: Programming Language :: Python :: 3.11
Classifier: Programming Language :: Python :: 3.12
Classifier: Programming Language :: Python :: 3.13
Project-URL: Repository, https://github.com/vil02/string_to_code_proj
